SystemVerilog/proodos/askhsh5.sv
module askhsh5(
	input logic clk,
	input logic rst,
	output logic tick,
	output logic [2:0] slow_cnt
);
	logic [1:0] cnt_cycle;
	
	always_ff @(posedge clk) begin
		if(rst)
			cnt_cycle <= 0;
		else begin
			cnt_cycle <= cnt_cycle + 1;
			
			if (cnt_cycle == 2) cnt_cycle <= 0;
			
		end
	end
	
	always_ff @(posedge clk) begin
		if(rst) begin
			tick <= 0;
			slow_cnt <= 0;
		end
		else begin
			if(cnt_cycle == 1) tick <= 1;
			else tick <= 0;
			
			if(cnt_cycle == 1) slow_cnt <= slow_cnt + 1;
		end
	end
	
endmodule

SystemVerilog/course-material/exams/exam1/askhsh5_test.sv
`timescale 1ns/1ps
module askhsh5_test;
logic clk,rst,tick;
logic [2:0] slow_cnt;

askhsh5 dut (.clk(clk), .rst(rst), .tick(tick), .slow_cnt(slow_cnt));

initial begin
clk = 0;
forever #5ns clk = ~clk;
end

initial begin
$dumpfile("dump5.vcd");
$dumpvars(1);
@(negedge clk);
#4ns;
rst = 1;
#5ns;
rst = 0;

#100ns;
$stop;
end

endmodule

SystemVerilog/course-material/exams/exam1/dump5.vcd
$date
	Thu Dec 01 14:33:33 2022
$end
$version
	Icarus Verilog
$end
$timescale
	1ps
$end
$scope module askhsh5_test $end
$var wire 1 ! tick $end
$var wire 3 " slow_cnt [2:0] $end
$var reg 1 # clk $end
$var reg 1 $ rst $end
$upscope $end
$enddefinitions $end
$comment Show the parameter values. $end
$dumpall
$end
#0
$dumpvars
x$
0#
bx "
x!
$end
#5000
0!
1#
#10000
0#
#14000
1$
#15000
b0 "
1#
#19000
0$
#20000
0#
#25000
1#
#30000
0#
#35000
b1 "
1!
1#
#40000
0#
#45000
0!
1#
#50000
0#
#55000
1#
#60000
0#
#65000
b10 "
1!
1#
#70000
0#
#75000
0!
1#
#80000
0#
#85000
1#
#90000
0#
#95000
b11 "
1!
1#
#100000
0#
#105000
0!
1#
