SystemVerilog/course-material/labs/lab1/checkTie.sv
module checkTie (
  input logic [2:0] inA,
  input logic [2:0] inB,
  output logic tie);
  
/*
  always_comb begin
    assign tie = 1'b1;
	
    for (int i=0; i < 2; i++) begin 
	  if ( inA[i] == inB[i] & tie == 1'b1 )
	    assign tie = 1'b1;
	  else
	    assign tie = 1'b0;
    end
  end
*/
  assign tie = (inA[0]^inB[0]) | (inA[1]^inB[1]) | (inA[2]^inB[2]);
endmodule

SystemVerilog/course-material/labs/labs_v1/lab1/winnerB.sv
module winnerB
(
  input logic [2:0] inA,
  input logic [2:0] inB,
  output logic winB
);

  /*
	Code Here
  */
  
endmodule

SystemVerilog/course-material/labs/labs_v1/lab1/winnerA.sv
module winnerA
(
  input logic [2:0] inA,
  input logic [2:0] inB,
  output logic winA
);

  /*
	Code Here
  */
  
endmodule

SystemVerilog/course-material/labs/labs_v1/lab1/validIO.sv
module validIO
(
  input logic [2:0] inA,
  input logic [2:0] inB,
  output logic valid
);

  /*
	Code Here
  */
  
endmodule

SystemVerilog/course-material/labs/labs_v1/lab1/RockPaperScissors.sv
module RockPaperScissors
(
  input logic [2:0] inA,
  input logic [2:0] inB,
  output logic valid,
  output logic tie,
  output logic winA,
  output logic winB
);

  // Check if the two inputs are valid moves
  validIO isVal(.inA(inA), .inB(inB), .valid(valid));
  
  // Check if the winner is player A
  winnerA winsA(.inA(inA), .inB(inB), .winA(winA));
  
  // Check if the winner is player B
  winnerB winsB(.inA(inA), .inB(inB), .winB(winB));
  
  // Check if the result is a tie
  checkTie isTie(.inA(inA), .inB(inB), .tie(tie));

endmodule

SystemVerilog/course-material/labs/lab1/RockPaperScissors_test.sv
// referencedesigner.com verilog tutorial
// testbench for RockPaperScissors.sv
`timescale 1ns / 1ps
module RockPaperScissors_test;
	// Inputs
	logic [2:0] inA , inB;
	// Outputs
	logic valid, tie, winA, winB;
	// Instantiate the Unit Under Test (UUT)
	// Here the name is RockPaperScissors
	RockPaperScissors uut(
		.inA(inA), 
		.inB(inB), 
		.valid(valid),
		.tie(tie),
		.winA(winA),
		.winB(winB)
	);
 
	initial begin
	//observer the variables and print their values
	// if at least one change its value
	$monitor($time, "A=%b,B=%b,valid=%b,tie=%b,winA=%b,winB=%b \n",inA,inB,valid,tie,winA,winB);
	$dumpfile("dump.vcd");
	$dumpvars(1);
	// Initialize Inputs
	inA = 3'b000;
	inB = 3'b000;
	#10;
	
	inA = 3'b001;
	inB = 3'b000;
	#10;
	
	inA = 3'b000;
	inB = 3'b111;
	#10;
	
	inA = 3'b010;
	inB = 3'b001;
	#10;
	
	inA = 3'b100;
	inB = 3'b001;
	#10;
	
	inA = 3'b010;
	inB = 3'b010;
	#10;
	
	inA = 3'b001;
	inB = 3'b101;
	#10;
	
	inA = 3'b010;
	inB = 3'b100;
	#10;
	
	end
endmodule

SystemVerilog/course-material/labs/lab1/dump.vcd
$date
	Tue Jan 24 20:31:05 2023
$end
$version
	Icarus Verilog
$end
$timescale
	1ps
$end
$scope module RockPaperScissors_test $end
$var wire 1 ! winB $end
$var wire 1 " winA $end
$var wire 1 # valid $end
$var wire 1 $ tie $end
$var reg 3 % inA [2:0] $end
$var reg 3 & inB [2:0] $end
$upscope $end
$enddefinitions $end
$comment Show the parameter values. $end
$dumpall
$end
#0
$dumpvars
b0 &
b0 %
0$
0#
0"
0!
$end
#10000
1$
b1 %
#20000
b111 &
b0 %
#30000
1#
1!
b1 &
b10 %
#40000
1#
1"
0!
b100 %
#50000
0$
0"
b10 &
b10 %
#60000
0#
1$
b101 &
b1 %
#70000
1#
1"
b100 &
b10 %
