SystemVerilog/set4/ex1/copy_queue.sv

module copy_queue
#(
    parameter int DW    = 8,
    parameter int DEPTH = 4
)
(
    input  logic            clk,
    input  logic            rst,
    // input channel
    input  logic[DW-1:0]    write_data,
    input  logic            push,
    output logic            full,
    // output channel
    output logic[DW-1:0]    read_data,
    output logic            empty,
    input  logic            pop
);
 
logic[DEPTH-1:0][DW-1:0]    mem;
logic[DEPTH-1:0]            tail;
logic[DEPTH-1:0]            head;
logic[DEPTH  :0]            status_cnt;

assign empty = status_cnt[0];
assign full = status_cnt[DEPTH];

//Pointer update (one-hot shifting pointers)
always_ff @ (posedge clk, posedge rst) begin: ff_tail
    if (rst) begin
        tail <= 0;
    end else begin
        // push pointer
        if (push && (pop || !full)) begin
            tail <= tail + 1;
            if (tail == DEPTH-1)
              tail <= 0;
        end
    end
end
always_ff @ (posedge clk, posedge rst) begin: ff_head
    if (rst) begin
        head <= 0;
    end else begin
        // pop pointer
        if (pop && !empty) begin
            head <= head + 1;
            if (head == DEPTH-1)
              head <= 0;
        end
    end
end
    
// Status (occupied slots) Counter
always_ff @ (posedge clk, posedge rst) begin: ff_status_cnt
    if (rst) begin
        status_cnt <= 1; // status counter onehot coded
    end else begin
        if (push & ~pop & ~full) begin
            // shift left status counter (increment)
            status_cnt <= { status_cnt[DEPTH-1:0],1'b0 } ;
        end else if (~push &  pop & ~empty) begin
            // shift right status counter (decrement)
            status_cnt <= {1'b0, status_cnt[DEPTH:1] };
        end
    end
end
 
// data write (push) 
// address decoding needed for onehot push pointer
always_ff @ (posedge clk) begin: ff_reg_dec
    if ( push && ( pop || !full)) begin
        mem[tail] <= write_data;
    end
end

assign read_data = mem[head];

endmodule

SystemVerilog/fifo/fifo_duth.sv
/**
 * @info fifo_duth
 *
 * @author VLSI Lab, EE dept., Democritus University of Thrace
 *
 * @brief FIFO circular buffer. Uses an input decoder to store to the proper place and an output MUX to select the proper output data.
 *
 * @param DW data width
 * @param DEPTH number of buffer slots. Note: If 1, leads to 50% throughput, so use @see eb_one_slot with FULL_THROUGHPUT asserted.
 */
 
module fifo_duth
#(
    parameter int DW    = 16,
    parameter int DEPTH = 4
)
(
    input  logic            clk,
    input  logic            rst,
    // input channel
    input  logic[DW-1:0]    write_data,
    input  logic            push,
    output logic            full,
    // output channel
    output logic[DW-1:0]    read_data,
    output logic            empty,
    input  logic            pop
);
    
logic[DEPTH-1:0][DW-1:0]    mem;
logic[DEPTH-1:0]            tail;
logic[DEPTH-1:0]            head;
logic[DEPTH  :0]            status_cnt;

assign empty = status_cnt[0];
assign full = status_cnt[DEPTH];

//Pointer update (one-hot shifting pointers)
always_ff @ (posedge clk, posedge rst) begin: ff_tail
    if (rst) begin
        tail <= 0;
    end else begin
        // push pointer
        if (push && (pop || !full)) begin
            tail <= tail + 1;
            if (tail == DEPTH-1)
              tail <= 0;
        end
    end
end
always_ff @ (posedge clk, posedge rst) begin: ff_head
    if (rst) begin
        head <= 0;
    end else begin
        // pop pointer
        if (pop && !empty) begin
            head <= head + 1;
            if (head == DEPTH-1)
              head <= 0;
        end
    end
end
    
// Status (occupied slots) Counter
always_ff @ (posedge clk, posedge rst) begin: ff_status_cnt
    if (rst) begin
        status_cnt <= 1; // status counter onehot coded
    end else begin
        if (push & ~pop & ~full) begin
            // shift left status counter (increment)
            status_cnt <= { status_cnt[DEPTH-1:0],1'b0 } ;
        end else if (~push &  pop & ~empty) begin
            // shift right status counter (decrement)
            status_cnt <= {1'b0, status_cnt[DEPTH:1] };
        end
    end
end
 
// data write (push) 
// address decoding needed for onehot push pointer
always_ff @ (posedge clk) begin: ff_reg_dec
    if ( push && ( pop || !full)) begin
        mem[tail] <= write_data;
    end
end

assign read_data = mem[head];

endmodule

SystemVerilog/course-material/sets-of-exercises/set4/ex1/duplicate_fifo.sv

module duplicate_fifo
#(
    parameter int DW    = 8,
    parameter int DEPTH = 4
)
(
    input  logic            clk,
    input  logic            rst,
    // input channel
    input  logic[DW-1:0]    data_in,
    input  logic            write,
    output logic            full,
    // output channel
    output logic[DW-1:0]    data_out,
    output logic            empty,
    input  logic            read
);

logic [DW-1:0] data;
logic pop_internal;
logic empty_internal;
logic push_internal;
logic full_internal;

fifo_duth 
#(
  .DW(DW),
  .DEPTH(DEPTH))
DUT1 (
  .clk(clk),
  .rst(rst),
  .write_data(data_in),
  .push(write),
  .full(full),
  .read_data(data),
  .pop(pop_internal),
  .empty(empty_internal)
);

assign pop_internal = ~empty_internal & ~full_internal;
assign push_internal = ~empty_internal & ~full_internal;

copy_queue
#(
    .DW(DW),
    .DEPTH(DEPTH))
DUT2 (
  .clk(clk),
  .rst(rst),
  .write_data(data),
  .push(push_internal),
  .full(full_internal),
  .read_data(data_out),
  .pop(pop_read),
  .empty(empty)
);

logic pop_read;
logic cnt_reads;
logic[1:0] cnt;

always_ff @(posedge clk) begin: count_reads
    if(rst)
        cnt <= 0;
    else begin
        if(read)
            cnt <= cnt + 1;
    end
end
/*
always_ff @(posedge clk) begin: count_2_reads
    if (rst)
        cnt_reads <= 0;
    else begin
        if(read && !empty) begin
            //if we try to read and it is not empty then reads counter counts + 1.
            cnt_reads <= 0;
        end else if(!read && !cnt_reads) begin
            if(cnt==1 || cnt == 3)
                cnt_reads <= 1;
        end
    end
end

always_ff@(posedge clk) begin: when_to_pop
    if(rst)
        pop_read <= 0;
    else begin
        if(cnt_reads)
            pop_read <= 1;
        else
            pop_read <= 0;
    end
end
*/
always_ff @(posedge clk) begin: count_2_reads
    if (rst) begin
        cnt_reads <= 0;
        pop_read <= 0;
    end else begin
        if((!read && !cnt_reads) && (cnt==1 || cnt == 3))
            cnt_reads <= 1;
        else if(read && !empty)
            cnt_reads <= 0;
        
        if(cnt_reads)
            pop_read <= 1;
        else
            pop_read <= 0;
    end
end

endmodule

SystemVerilog/set4/ex1/test.sv
`timescale 1ns/1ps

module test;


parameter DW = 8;
parameter DEPTH = 4;

logic clk;
logic rst;
logic [DW-1:0] din_i;
logic write_i;
logic full_o;
logic [DW-1:0] dout_o;
logic read_i;
logic empty_o;

// generate clock signal
always begin
  clk = 1;
  #5ns;
  clk = 0;
  #5ns;
end

duplicate_fifo dut (
  .clk(clk),
  .rst(rst),
  .data_in(din_i),
  .write(write_i),
  .full(full_o),
  .data_out(dout_o),
  .read(read_i),
  .empty(empty_o)
);

initial begin
  $dumpfile("dumpset1.vcd");
  $dumpvars(1);
  $display("Starting Simulation");
  write_i <= 0;  // Set starting values
  read_i  <= 0;
  rst     <= 0;
  din_i   <= 0;

  @(posedge clk); // First positive edge of the clock 
  rst <= 1;
  @(posedge clk); // Second positive edge of the clock
  rst <= 0;
  @(posedge clk);
  
  // Demo Simulation example
  PUSH(1);
  PUSH(2);
  PUSH(3);
  PUSH(4);
  PUSH(5);
  repeat(10) begin
    POP();
  end
  PUSH(5);
  // End of demo simulation example
  
  
  // Extra simulation example
  write_i <= 1;         // start push
  din_i <= 7;
  @(posedge clk);
  din_i <= 14;
  @(posedge clk);
  din_i <= 4;            
  read_i <= 1;          // start pop
  $strobe("Read data -> %d", dout_o);
  @(posedge clk);    // From now on push and pop happen together
  din_i <= 13;
  $strobe("Read data -> %d", dout_o);
  @(posedge clk);
  din_i <= 25;
  $strobe("Read data -> %d", dout_o);
  @(posedge clk);
  din_i <= 32;
  $strobe("Read data -> %d", dout_o);
  @(posedge clk);
  din_i <= 9;
  $strobe("Read data -> %d", dout_o);
  @(posedge clk);
  read_i <= 0;          // Stop pop
  din_i <= 21;
  @(posedge clk);    // From now on data should not be stored in FIFO because its full
  din_i <= 22;
  @(posedge clk);
  din_i <= 23;
  @(posedge clk);
  din_i <= 24;
  read_i <= 1;          // Start pop
  @(posedge clk);    // From now on push and pop happen together
  $strobe("Read data -> %d", dout_o);
  din_i <= 51;
  @(posedge clk);    
  $strobe("Read data -> %d", dout_o);
  write_i <= 0;         // Stop push
  din_i <= 21;          // 21 will not be stored in FIFO because push is 0
  @(posedge clk);   
  $strobe("Read data -> %d", dout_o);
  din_i <= 20;         // 20 will not be stored in FIFO because push is 0
  @(posedge clk);    
  $strobe("Read data -> %d", dout_o);
  @(posedge clk);    
  $strobe("Read data -> %d", dout_o);
  @(posedge clk);   
  $strobe("Read data -> %d", dout_o);
  @(posedge clk);    // From now on dout_o has the same value because FIFO is empty;
  $strobe("Read data -> %d", dout_o);
  read_i <= 0;
  @(posedge clk)
  
  
  
  $display("Simulation Finished");
  $stop();
end

task PUSH(input [DW-1:0] X); 
  begin
    write_i <= 1;
    din_i <= X;
    @(posedge clk);
    //$strobe("@%0t: Fifo values are: %d, %d, %d, %d", $time, dut.mem[0], dut.mem[1], dut.mem[2], dut.mem[3]);
    write_i <= 0;
    @(posedge clk);
  end
endtask

task POP(); 
  begin
    read_i <= 1;
    $strobe("@%0t: Read data -> %d", $time, dout_o);
    @(posedge clk);
    read_i <= 0;
    @(posedge clk);
  end
endtask

endmodule

SystemVerilog/set4/ex1/dumpset1.vcd
$date
	Sun Dec 18 21:01:18 2022
$end
$version
	Icarus Verilog
$end
$timescale
	1ps
$end
$scope module test $end
$var wire 1 ! full_o $end
$var wire 1 " empty_o $end
$var wire 8 # dout_o [7:0] $end
$var parameter 32 $ DEPTH $end
$var parameter 32 % DW $end
$var reg 1 & clk $end
$var reg 8 ' din_i [7:0] $end
$var reg 1 ( read_i $end
$var reg 1 ) rst $end
$var reg 1 * write_i $end
$upscope $end
$enddefinitions $end
$comment Show the parameter values. $end
$dumpall
b1000 %
b100 $
$end
#0
$dumpvars
0*
0)
0(
b0 '
1&
bx #
x"
x!
$end
#5000
0&
#10000
1"
0!
1)
1&
#15000
0&
#20000
0)
1&
#25000
0&
#30000
b1 '
1*
1&
#35000
0&
#40000
0*
1&
#45000
0&
#50000
0"
b1 #
b10 '
1*
1&
#55000
0&
#60000
0*
1&
#65000
0&
#70000
b11 '
1*
1&
#75000
0&
#80000
0*
1&
#85000
0&
#90000
b100 '
1*
1&
#95000
0&
#100000
0*
1&
#105000
0&
#110000
b101 '
1*
1&
#115000
0&
#120000
0*
1&
#125000
0&
#130000
1(
1&
#135000
0&
#140000
0(
1&
#145000
0&
#150000
1(
1&
#155000
0&
#160000
0(
1&
#165000
0&
#170000
b10 #
1(
1&
#175000
0&
#180000
0(
1&
#185000
0&
#190000
1(
1&
#195000
0&
#200000
0(
1&
#205000
0&
#210000
b11 #
1(
1&
#215000
0&
#220000
0(
1&
#225000
0&
#230000
1(
1&
#235000
0&
#240000
0(
1&
#245000
0&
#250000
b100 #
1(
1&
#255000
0&
#260000
0(
1&
#265000
0&
#270000
1(
1&
#275000
0&
#280000
0(
1&
#285000
0&
#290000
b101 #
1(
1&
#295000
0&
#300000
0(
1&
#305000
0&
#310000
1(
1&
#315000
0&
#320000
0(
1&
#325000
0&
#330000
1"
b10 #
1*
1&
#335000
0&
#340000
0*
1&
#345000
0&
#350000
0"
b101 #
b111 '
1*
1&
#355000
0&
#360000
b1110 '
1&
#365000
0&
#370000
1(
b100 '
1&
#375000
0&
#380000
b1101 '
1&
#385000
0&
#390000
b11001 '
1&
#395000
0&
#400000
b100000 '
1&
#405000
0&
#410000
b1001 '
1&
#415000
0&
#420000
1!
b10101 '
0(
1&
#425000
0&
#430000
b10110 '
1&
#435000
0&
#440000
b10111 '
1&
#445000
0&
#450000
b111 #
1(
b11000 '
1&
#455000
0&
#460000
b1110 #
b110011 '
1&
#465000
0&
#470000
b100 #
b10101 '
0*
1&
#475000
0&
#480000
0!
b10100 '
1&
#485000
0&
#490000
1&
#495000
0&
#500000
1&
#505000
0&
#510000
1&
#515000
0&
#520000
0(
1&
