SystemVerilog/course-material/sets-of-exercises/set4/fifo/fifo_duth.sv
/**
 * @info fifo_duth
 *
 * @author VLSI Lab, EE dept., Democritus University of Thrace
 *
 * @brief FIFO circular buffer. Uses an input decoder to store to the proper place and an output MUX to select the proper output data.
 *
 * @param DW data width
 * @param DEPTH number of buffer slots. Note: If 1, leads to 50% throughput, so use @see eb_one_slot with FULL_THROUGHPUT asserted.
 */
 
module fifo_duth
#(
    parameter int DW    = 16,
    parameter int DEPTH = 4
)
(
    input  logic            clk,
    input  logic            rst,
    // input channel
    input  logic[DW-1:0]    write_data,
    input  logic            push,
    output logic            full,
    // output channel
    output logic[DW-1:0]    read_data,
    output logic            empty,
    input  logic            pop
);
    
logic[DEPTH-1:0][DW-1:0]    mem;
logic[DEPTH-1:0]            tail;
logic[DEPTH-1:0]            head;
logic[DEPTH  :0]            status_cnt;

assign empty = status_cnt[0];
assign full = status_cnt[DEPTH];

//Pointer update (one-hot shifting pointers)
always_ff @ (posedge clk, posedge rst) begin: ff_tail
    if (rst) begin
        tail <= 0;
    end else begin
        // push pointer
        if (push && (pop || !full)) begin
            tail <= tail + 1;
            if (tail == DEPTH-1)
              tail <= 0;
        end
    end
end
always_ff @ (posedge clk, posedge rst) begin: ff_head
    if (rst) begin
        head <= 0;
    end else begin
        // pop pointer
        if (pop && !empty) begin
            head <= head + 1;
            if (head == DEPTH-1)
              head <= 0;
        end
    end
end
    
// Status (occupied slots) Counter
always_ff @ (posedge clk, posedge rst) begin: ff_status_cnt
    if (rst) begin
        status_cnt <= 1; // status counter onehot coded
    end else begin
        if (push & ~pop & ~full) begin
            // shift left status counter (increment)
            status_cnt <= { status_cnt[DEPTH-1:0],1'b0 } ;
        end else if (~push &  pop & ~empty) begin
            // shift right status counter (decrement)
            status_cnt <= {1'b0, status_cnt[DEPTH:1] };
        end
    end
end
 
// data write (push) 
// address decoding needed for onehot push pointer
always_ff @ (posedge clk) begin: ff_reg_dec
    if ( push && ( pop || !full)) begin
        mem[tail] <= write_data;
    end
end

assign read_data = mem[head];

endmodule

SystemVerilog/course-material/sets-of-exercises/set4/fifo/fifo_tb.sv
`timescale 1ns/1ps

module fifo_tb;

parameter DW = 16;
parameter DEPTH = 4;

logic clk, rst;
logic push, pop, full, empty;
logic [DW-1:0] wd, rd;

// Instantitation of our design
fifo_duth #(.DW(DW), .DEPTH(DEPTH)) dut(
  .clk        (clk),
  .rst        (rst),
  .push       (push),
  .write_data (wd),
  .full       (full),
  .pop        (pop),
  .read_data  (rd),
  .empty      (empty)
);

// generate clock signal
/*initial begin
clk = 0;
forever #5ns clk = ~clk;
end*/
always begin
  clk = 1;
  #5ns;
  clk = 0;
  #5ns;
end

initial begin
  $monitor($time);
  $dumpfile("dumpfifo.vcd");
  $dumpvars(1);
  $monitor("Starting Simulation");
  push <= 0;  // Set starting values
  pop  <= 0;
  rst  <= 0;
  wd   <= 0;

  @(posedge clk); // First positive edge of the clock 
  rst <= 1;
  @(posedge clk); // Second positive edge of the clock
  rst <= 0;
  @(posedge clk);
  
  // Demo Simulation example
  PUSH(1);
  PUSH(2);
  PUSH(3);
  PUSH(4);
  PUSH(5);
  repeat(5) begin
    POP();
  end
  PUSH(5);
  // End of demo simulation example
  
  
  // Extra simulation example
  push <= 1;         // start push
  wd <= 7;
  @(posedge clk);
  wd <= 14;
  @(posedge clk);
  wd <= 4;            
  pop <= 1;          // start pop
  $strobe("Read data -> %d", rd);
  @(posedge clk);    // From now on push and pop happen together
  wd <= 13;
  $strobe("Read data -> %d", rd);
  @(posedge clk);
  wd <= 25;
  $strobe("Read data -> %d", rd);
  @(posedge clk);
  wd <= 32;
  $strobe("Read data -> %d", rd);
  @(posedge clk);
  wd <= 9;
  $strobe("Read data -> %d", rd);
  @(posedge clk);
  pop <= 0;          // Stop pop
  wd <= 21;
  @(posedge clk);    // From now on data should not be stored in FIFO because its full
  wd <= 22;
  @(posedge clk);
  wd <= 23;
  @(posedge clk);
  wd <= 24;
  pop <= 1;          // Start pop
  @(posedge clk);    // From now on push and pop happen together
  $strobe("Read data -> %d", rd);
  wd <= 51;
  @(posedge clk);    
  $strobe("Read data -> %d", rd);
  push <= 0;         // Stop push
  wd <= 21;          // 21 will not be stored in FIFO because push is 0
  @(posedge clk);   
  $strobe("Read data -> %d", rd);
  wd <= 20;         // 20 will not be stored in FIFO because push is 0
  @(posedge clk);    
  $strobe("Read data -> %d", rd);
  @(posedge clk);    
  $strobe("Read data -> %d", rd);
  @(posedge clk);   
  $strobe("Read data -> %d", rd);
  @(posedge clk);    // From now on rd has the same value because FIFO is empty;
  $strobe("Read data -> %d", rd);
  pop <= 0;
  @(posedge clk)
  
  
  
  $display("Simulation Finished");
  $stop();
end

task PUSH(input [DW-1:0] X); 
  begin
    push <= 1;
    wd <= X;
    @(posedge clk);
    //$strobe("@%0t: Fifo values are: %d, %d, %d, %d", $time, DUT.mem[0], DUT.mem[1], DUT.mem[2], DUT.mem[3]);
    push <= 0;
    @(posedge clk);
  end
endtask

task POP(); 
  begin
    pop <= 1;
    $strobe("@%0t: Read data -> %d", $time, rd);
    @(posedge clk);
    pop <= 0;
    @(posedge clk);
  end
endtask



endmodule

SystemVerilog/course-material/sets-of-exercises/set4/fifo/dumpfifo.vcd
$date
	Sat Dec 17 17:31:22 2022
$end
$version
	Icarus Verilog
$end
$timescale
	1ps
$end
$scope module fifo_tb $end
$var wire 16 ! rd [15:0] $end
$var wire 1 " full $end
$var wire 1 # empty $end
$var parameter 32 $ DEPTH $end
$var parameter 32 % DW $end
$var reg 1 & clk $end
$var reg 1 ' pop $end
$var reg 1 ( push $end
$var reg 1 ) rst $end
$var reg 16 * wd [15:0] $end
$upscope $end
$enddefinitions $end
$comment Show the parameter values. $end
$dumpall
b10000 %
b100 $
$end
#0
$dumpvars
b0 *
0)
0(
0'
1&
x#
x"
bx !
$end
#5000
0&
#10000
1#
0"
1)
1&
#15000
0&
#20000
0)
1&
#25000
0&
#30000
b1 *
1(
1&
#35000
0&
#40000
0#
b1 !
0(
1&
#45000
0&
#50000
b10 *
1(
1&
#55000
0&
#60000
0(
1&
#65000
0&
#70000
b11 *
1(
1&
#75000
0&
#80000
0(
1&
#85000
0&
#90000
b100 *
1(
1&
#95000
0&
#100000
1"
0(
1&
#105000
0&
#110000
b101 *
1(
1&
#115000
0&
#120000
0(
1&
#125000
0&
#130000
1'
1&
#135000
0&
#140000
0"
b10 !
0'
1&
#145000
0&
#150000
1'
1&
#155000
0&
#160000
b11 !
0'
1&
#165000
0&
#170000
1'
1&
#175000
0&
#180000
b100 !
0'
1&
#185000
0&
#190000
1'
1&
#195000
0&
#200000
1#
b1 !
0'
1&
#205000
0&
#210000
1'
1&
#215000
0&
#220000
0'
1&
#225000
0&
#230000
1(
1&
#235000
0&
#240000
0#
b101 !
0(
1&
#245000
0&
#250000
b111 *
1(
1&
#255000
0&
#260000
b1110 *
1&
#265000
0&
#270000
1'
b100 *
1&
#275000
0&
#280000
b111 !
b1101 *
1&
#285000
0&
#290000
b1110 !
b11001 *
1&
#295000
0&
#300000
b100 !
b100000 *
1&
#305000
0&
#310000
b1101 !
b1001 *
1&
#315000
0&
#320000
b11001 !
b10101 *
0'
1&
#325000
0&
#330000
1"
b10110 *
1&
#335000
0&
#340000
b10111 *
1&
#345000
0&
#350000
1'
b11000 *
1&
#355000
0&
#360000
b100000 !
b110011 *
1&
#365000
0&
#370000
b1001 !
b10101 *
0(
1&
#375000
0&
#380000
0"
b10101 !
b10100 *
1&
#385000
0&
#390000
b11000 !
1&
#395000
0&
#400000
b110011 !
1&
#405000
0&
#410000
1#
b1001 !
1&
#415000
0&
#420000
0'
1&
